crcc-2.1.0.dist-info/METADATA
crcc-2.1.0.dist-info/RECORD
crcc-2.1.0.dist-info/WHEEL
crcc-2.1.0.dist-info/licenses/LICENSE
crcc-2.1.0.dist-info/top_level.txt
crcc/_platform/crc.pypy310-pp73-win_amd64.pyd
crcc/py.typed
crcc\__about__.pyc
crcc\__init__.pyc
crcc\_crc.pyc
crcc\_dll.pyc
crcc\_platform\__init__.pyc
crcc\_platform\linux\__init__.pyc
crcc\_platform\macos\__init__.pyc
crcc\_platform\windows\__init__.pyc
